{"version":1,"resource":"vscode-remote://ssh-remote%2B192.168.74.129/home/longvu/nachos/NachOS-4.0/code/userprog/ksyscall.h","entries":[{"id":"xqX8.h","timestamp":1677945787404},{"id":"PRpO.h","source":"undoRedo.source","timestamp":1677945812624},{"id":"pobr.h","timestamp":1677945817928},{"id":"dsfY.h","source":"undoRedo.source","timestamp":1677945820412},{"id":"8v5B.h","timestamp":1677945821124},{"id":"8ygk.h","timestamp":1678024523409},{"id":"ASjc.h","timestamp":1678025668052},{"id":"dkzM.h","timestamp":1678028734900},{"id":"xAV6.h","timestamp":1678028746648}]}